statina/__init__.py
statina/config.py
statina/constants.py
statina/exeptions.py
statina/main.py
statina/API/__init__.py
statina/API/external/__init__.py
statina/API/external/constants.py
statina/API/external/api/__init__.py
statina/API/external/api/deps.py
statina/API/external/api/api_v1/__init__.py
statina/API/external/api/api_v1/endpoints/__init__.py
statina/API/external/api/api_v1/endpoints/batches.py
statina/API/external/api/api_v1/endpoints/index.py
statina/API/v2/__init__.py
statina/API/v2/endpoints/__init__.py
statina/API/v2/endpoints/base.py
statina/API/v2/endpoints/batches.py
statina/API/v2/endpoints/sample.py
statina/API/v2/endpoints/statistics.py
statina/API/v2/endpoints/user.py
statina/adapter/__init__.py
statina/adapter/plugin.py
statina/crud/__init__.py
statina/crud/insert.py
statina/crud/update.py
statina/crud/utils.py
statina/crud/find/__init__.py
statina/crud/find/batches.py
statina/crud/find/samples.py
statina/crud/find/users.py
statina/crud/find/plots/__init__.py
statina/crud/find/plots/coverage_plot_data.py
statina/crud/find/plots/fetal_fraction_plot_data.py
statina/crud/find/plots/statistics_plot_data.py
statina/crud/find/plots/zscore_plot_data.py
statina/models/__init__.py
statina/models/query_params.py
statina/models/database/__init__.py
statina/models/database/batch.py
statina/models/database/dataset.py
statina/models/database/sample.py
statina/models/database/user.py
statina/models/server/__init__.py
statina/models/server/auth.py
statina/models/server/batch.py
statina/models/server/load.py
statina/models/server/new_user.py
statina/models/server/sample.py
statina/models/server/plots/__init__.py
statina/models/server/plots/coverage.py
statina/models/server/plots/fetal_fraction.py
statina/models/server/plots/fetal_fraction_sex.py
statina/models/server/plots/fetal_fraction_sex_model.py
statina/models/server/plots/ncv.py
statina/parse/__init__.py
statina/parse/batch.py
tests/__init__.py
tests/conftest.py
tests/small_helpers.py
statina-2.9.1.dist-info/METADATA
statina-2.9.1.dist-info/WHEEL
statina-2.9.1.dist-info/top_level.txt
statina-2.9.1.dist-info/RECORD
