Metadata-Version: 2.1
Name: statina
Version: 2.9.1
Summary: NIPT data storage and visualisation
Home-page: https://github.com/Clinical-Genomics/statina
Author: Maya Brandi
Author-email: maya.brandi@scilifelab.se
License: UNKNOWN
Platform: UNKNOWN
Classifier: Programming Language :: Python :: 3
Classifier: License :: OSI Approved :: MIT License
Classifier: Operating System :: OS Independent
Requires-Python: >=3.6
Requires-Dist: click
Requires-Dist: bump2version
Requires-Dist: pymongo
Requires-Dist: mongo-adapter
Requires-Dist: coloredlogs
Requires-Dist: pyyaml
Requires-Dist: cerberus
Requires-Dist: python-multipart
Requires-Dist: python-dotenv
Requires-Dist: email-validator
Requires-Dist: jinja2
Requires-Dist: passlib
Requires-Dist: fastapi
Requires-Dist: uvicorn
Requires-Dist: uvloop
Requires-Dist: httptools
Requires-Dist: gunicorn
Requires-Dist: python-jose[cryptography]
Requires-Dist: bcrypt
Requires-Dist: numpy
Requires-Dist: aiofiles
Requires-Dist: sendmail-container
